odoo10_addon_purchase_product_multi_add-10.0.1.0.0.99.dev4-py3.8-nspkg.pth
odoo/addons/purchase_product_multi_add/README.rst
odoo/addons/purchase_product_multi_add/__init__.py
odoo/addons/purchase_product_multi_add/__manifest__.py
odoo/addons/purchase_product_multi_add/i18n/purchase_product_multi_add.pot
odoo/addons/purchase_product_multi_add/readme/CONTRIBUTORS.rst
odoo/addons/purchase_product_multi_add/readme/DESCRIPTION.rst
odoo/addons/purchase_product_multi_add/readme/USAGE.rst
odoo/addons/purchase_product_multi_add/static/description/icon.png
odoo/addons/purchase_product_multi_add/static/description/index.html
odoo/addons/purchase_product_multi_add/tests/__init__.py
odoo/addons/purchase_product_multi_add/tests/test_purchase.py
odoo/addons/purchase_product_multi_add/views/purchase_view.xml
odoo/addons/purchase_product_multi_add/wizard/__init__.py
odoo/addons/purchase_product_multi_add/wizard/purchase_import_products.py
odoo/addons/purchase_product_multi_add/wizard/purchase_import_products_view.xml
odoo10_addon_purchase_product_multi_add-10.0.1.0.0.99.dev4.dist-info/METADATA
odoo10_addon_purchase_product_multi_add-10.0.1.0.0.99.dev4.dist-info/WHEEL
odoo10_addon_purchase_product_multi_add-10.0.1.0.0.99.dev4.dist-info/namespace_packages.txt
odoo10_addon_purchase_product_multi_add-10.0.1.0.0.99.dev4.dist-info/top_level.txt
odoo10_addon_purchase_product_multi_add-10.0.1.0.0.99.dev4.dist-info/RECORD
