Metadata-Version: 2.1
Name: odoo10-addon-purchase-product-multi-add
Version: 10.0.1.0.0.99.dev4
Summary: This module allows a shortcut to add purchase.order.line by selecting product into a wizard for the given suplier
Home-page: https://github.com/OCA/purchase-workflow
Author: ACSONE SA/NV, Odoo Community Association (OCA)
Author-email: support@odoo-community.org
License: AGPL-3
Platform: UNKNOWN
Classifier: Programming Language :: Python
Classifier: Framework :: Odoo
Classifier: Framework :: Odoo :: 10.0
Classifier: License :: OSI Approved :: GNU Affero General Public License v3
Requires-Python: ~=2.7
Requires-Dist: odoo <10.1dev,>=10.0
